PachongZhiLu/README.md
PachongZhiLu/__init__.py
PachongZhiLu/__main__.py
PachongZhiLu/file.epub
PachongZhiLu/index.html
PachongZhiLu/css/__init__.py
PachongZhiLu/css/annotations.css
PachongZhiLu/css/main.css
PachongZhiLu/css/normalize.css
PachongZhiLu/css/popup.css
PachongZhiLu/font/__init__.py
PachongZhiLu/font/fontello.eot
PachongZhiLu/font/fontello.svg
PachongZhiLu/font/fontello.ttf
PachongZhiLu/font/fontello.woff
PachongZhiLu/img/__init__.py
PachongZhiLu/img/annotator-glyph-sprite.png
PachongZhiLu/img/annotator-icon-sprite.png
PachongZhiLu/img/apple-touch-icon.png
PachongZhiLu/img/cancelfullscreen.png
PachongZhiLu/img/close.png
PachongZhiLu/img/fullscreen.png
PachongZhiLu/img/loader.gif
PachongZhiLu/img/menu-icon.png
PachongZhiLu/img/save.png
PachongZhiLu/img/saved.png
PachongZhiLu/img/settings-s.png
PachongZhiLu/img/settings.png
PachongZhiLu/img/star.png
PachongZhiLu/js/__init__.py
PachongZhiLu/js/epub.js
PachongZhiLu/js/epub.min.js
PachongZhiLu/js/epub.min.map
PachongZhiLu/js/hooks.min.js
PachongZhiLu/js/hooks.min.map
PachongZhiLu/js/reader.js
PachongZhiLu/js/reader.js.map
PachongZhiLu/js/reader.min.js
PachongZhiLu/js/reader.min.map
PachongZhiLu/js/hooks/__init__.py
PachongZhiLu/js/hooks/extensions/__init__.py
PachongZhiLu/js/hooks/extensions/highlight.js
PachongZhiLu/js/libs/__init__.py
PachongZhiLu/js/libs/jquery.min.js
PachongZhiLu/js/libs/localforage.min.js
PachongZhiLu/js/libs/screenfull.js
PachongZhiLu/js/libs/screenfull.min.js
PachongZhiLu/js/libs/zip.min.js
PachongZhiLu/js/plugins/__init__.py
PachongZhiLu/js/plugins/hypothesis.js
PachongZhiLu/js/plugins/search.js
pachong_zhi_lu-2024.3.3.0.dist-info/METADATA
pachong_zhi_lu-2024.3.3.0.dist-info/WHEEL
pachong_zhi_lu-2024.3.3.0.dist-info/entry_points.txt
pachong_zhi_lu-2024.3.3.0.dist-info/top_level.txt
pachong_zhi_lu-2024.3.3.0.dist-info/RECORD
